seeqret/__init__.py
seeqret/cli_group_add.py
seeqret/cli_group_rm.py
seeqret/cli_group_server.py
seeqret/console_utils.py
seeqret/db_utils.py
seeqret/fileutils.py
seeqret/filterspec.py
seeqret/main.py
seeqret/run_utils.py
seeqret/seeqret_add.py
seeqret/seeqret_init.py
seeqret/seeqret_transfer.py
seeqret/migrations/__init__.py
seeqret/migrations/db_v_001.py
seeqret/migrations/db_v_002.py
seeqret/migrations/initialize_database.py
seeqret/migrations/utils.py
seeqret/models/__init__.py
seeqret/models/jason.py
seeqret/models/secret.py
seeqret/models/user.py
seeqret/seeqrypt/__init__.py
seeqret/seeqrypt/aes_fernet.py
seeqret/seeqrypt/nacl_backend.py
seeqret/seeqrypt/utils.py
seeqret/serializers/__init__.py
seeqret/serializers/command_serializer.py
seeqret/serializers/env_serializer.py
seeqret/serializers/insecure_json.py
seeqret/serializers/json_utils.py
seeqret/serializers/jsoncrypt_serializer.py
seeqret/serializers/serializer.py
seeqret/storage/__init__.py
seeqret/storage/get_secret.py
seeqret/storage/sqlite_storage.py
seeqret/storage/storage.py
seeqret-0.3.0.dist-info/licenses/LICENSE
tests/__init__.py
tests/clirunner_utils.py
tests/test_asymetric_encryption.py
tests/test_cli.py
tests/test_cli_add_key.py
tests/test_cli_add_user.py
tests/test_cli_backup.py
tests/test_cli_edit_value.py
tests/test_cli_env.py
tests/test_cli_info.py
tests/test_cli_init.py
tests/test_cli_introduction.py
tests/test_cli_keys.py
tests/test_cli_owner.py
tests/test_cli_rm_key.py
tests/test_cli_upgrade.py
tests/test_cli_users.py
tests/test_fileutils.py
tests/test_filterspec.py
tests/test_init_user.py
tests/test_jason.py
tests/test_migration_utils.py
tests/test_nacl_backend.py
tests/test_runutils.py
tests/test_seeqret_add.py
tests/test_seeqret_import.py
tests/test_seeqret_transfer.py
tests/test_seeqrypt_utils.py
tests/test_sign.py
tests/test_symetric_encryption.py
tests/performance/__init__.py
tests/performance/test_performance.py
seeqret-0.3.0.dist-info/METADATA
seeqret-0.3.0.dist-info/WHEEL
seeqret-0.3.0.dist-info/entry_points.txt
seeqret-0.3.0.dist-info/top_level.txt
seeqret-0.3.0.dist-info/RECORD
