Metadata-Version: 2.4
Name: seeqret
Version: 0.3.0
Summary: Safely transferring code secrets
Home-page: https://github.com/thebjorn/seeqret.git
Author: Bjorn
Keywords: secrets,gpg,pgp
Classifier: Programming Language :: Python :: 3
Classifier: License :: OSI Approved :: MIT License
Classifier: Operating System :: OS Independent
Classifier: Development Status :: 3 - Alpha
Classifier: Intended Audience :: Developers
Requires-Python: >3.10
License-File: LICENSE
Requires-Dist: rsa
Requires-Dist: python-gnupg
Requires-Dist: cryptography
Requires-Dist: pynacl
Requires-Dist: Click
Requires-Dist: rich
Requires-Dist: requests
Requires-Dist: pywin32; sys_platform == "win32"
Dynamic: author
Dynamic: classifier
Dynamic: description
Dynamic: description-content-type
Dynamic: home-page
Dynamic: keywords
Dynamic: license-file
Dynamic: requires-dist
Dynamic: requires-python
Dynamic: summary
